papershift/__init__.py
papershift/image_to_markdown.py
papershift/page_parser.py
papershift/pdf_converter.py
papershift/pdf_to_markdown.py
papershift-0.1.2.dist-info/METADATA
papershift-0.1.2.dist-info/WHEEL
papershift-0.1.2.dist-info/top_level.txt
papershift-0.1.2.dist-info/RECORD
