Metadata-Version: 2.4
Name: papershift
Version: 0.1.2
Summary: Convert PDF documents and images to Markdown format with AI assistance
Author: PDF to Markdown Team
License: MIT
Project-URL: Homepage, https://github.com/satish860/papershift
Project-URL: Bug Tracker, https://github.com/satish860/papershift/issues
Keywords: pdf,markdown,conversion,ai,image
Classifier: Development Status :: 4 - Beta
Classifier: Intended Audience :: Developers
Classifier: License :: OSI Approved :: MIT License
Classifier: Programming Language :: Python :: 3
Classifier: Programming Language :: Python :: 3.8
Classifier: Programming Language :: Python :: 3.9
Classifier: Programming Language :: Python :: 3.10
Classifier: Programming Language :: Python :: 3.11
Classifier: Programming Language :: Python :: 3.12
Requires-Python: >=3.8
Requires-Dist: PyMuPDF>=1.23.7
Requires-Dist: litellm>=1.0.0
Requires-Dist: openrouter>=0.2.0
Requires-Dist: python-dotenv>=0.19.0
Requires-Dist: Pillow>=10.0.0
Provides-Extra: dev
Requires-Dist: pytest>=7.0.0; extra == "dev"
Requires-Dist: black>=22.0.0; extra == "dev"
Requires-Dist: isort>=5.10.0; extra == "dev"
